dhooks_lite/__init__.py
dhooks_lite/client.py
dhooks_lite/constants.py
dhooks_lite/embed.py
dhooks_lite/serializers.py
dhooks_lite-1.1.0.dist-info/LICENSE
dhooks_lite-1.1.0.dist-info/WHEEL
dhooks_lite-1.1.0.dist-info/METADATA
dhooks_lite-1.1.0.dist-info/RECORD
