Metadata-Version: 2.1
Name: dhooks-lite
Version: 1.1.0
Summary: Another simple class wrapper for interacting with Discord webhooks.
Keywords: discord,discordhooks,discordwebhooks,webhooks
Author-email: Erik Kalkoken <kalkoken87@gmail.com>
Requires-Python: >=3.6
Classifier: Intended Audience :: Developers
Classifier: License :: OSI Approved :: MIT License
Classifier: Natural Language :: English
Classifier: Operating System :: OS Independent
Classifier: Programming Language :: Python
Classifier: Programming Language :: Python :: 3
Classifier: Programming Language :: Python :: 3.6
Classifier: Programming Language :: Python :: 3.7
Classifier: Programming Language :: Python :: 3.8
Classifier: Programming Language :: Python :: 3.9
Classifier: Programming Language :: Python :: 3.10
Classifier: Programming Language :: Python :: 3.11
Classifier: Topic :: Communications :: Chat
Classifier: Topic :: Software Development :: Libraries
Classifier: Topic :: Software Development :: Libraries :: Python Modules
Requires-Dist: requests
Project-URL: Changelog, https://gitlab.com/ErikKalkoken/dhooks-lite/-/blob/master/CHANGELOG.md
Project-URL: Documentation, https://dhooks-lite.readthedocs.io/en/latest/
Project-URL: Homepage, https://gitlab.com/ErikKalkoken/dhooks-lite
Project-URL: Source, https://gitlab.com/ErikKalkoken/dhooks-lite
Project-URL: Tracker, https://gitlab.com/ErikKalkoken/dhooks-lite/-/issues
